core/__init__.py
core/asgi.py
core/settings.py
core/urls.py
core/wsgi.py
tickle/__init__.py
tickle/admin.py
tickle/apps.py
tickle/models.py
tickle/tests.py
tickle/urls.py
tickle/views.py
tickle/migrations/0001_initial.py
tickle/migrations/0002_auto_20210226_0543.py
tickle/migrations/__init__.py
django_predrill_tickle-0.0.2.dist-info/LICENSE
django_predrill_tickle-0.0.2.dist-info/METADATA
django_predrill_tickle-0.0.2.dist-info/WHEEL
django_predrill_tickle-0.0.2.dist-info/top_level.txt
django_predrill_tickle-0.0.2.dist-info/RECORD
