Metadata-Version: 2.1
Name: django-predrill-tickle
Version: 0.0.2
Summary: A pluggable Django app for keeping rock climbing ticklists
Home-page: https://github.com/kerkeslager/tickle
Author: David Kerkeslager
Author-email: david@kerkeslager.com
License: AGPL3.0
Platform: UNKNOWN
Requires-Dist: Django
